dalle43/__init__.py
dalle43/dalle43.py
dalle43-0.0.0.6.dist-info/LICENSE.md
dalle43-0.0.0.6.dist-info/METADATA
dalle43-0.0.0.6.dist-info/WHEEL
dalle43-0.0.0.6.dist-info/top_level.txt
dalle43-0.0.0.6.dist-info/RECORD
