Metadata-Version: 2.1
Name: dalle43
Version: 0.0.0.6
Summary: Use OpenAI's DALL-E for free, unlimited and without politically correct restrictions
Author: 0ut0flin3
Author-email: 0ut0flin3 <0ut0flin3@protonmail.com>
License: Apache License
Project-URL: Homepage, https://github.com/0ut0flin3/dalle43
Keywords: DALL-E,openai,gpt-3
Classifier: License :: OSI Approved :: Apache Software License
Classifier: Programming Language :: Python
Classifier: Programming Language :: Python :: 3
Requires-Python: >=3
License-File: LICENSE.md
Requires-Dist: selenium (==4.8.2)
